<?xml version="1.0" encoding="utf-8" ?>
<dwsync>
<file name="._.DS_Store" server="www.plataformapse.com//www/openc3/" local="128741748940000000" remote="130849131000000000" Dst="0" />
<file name="._changelog.txt" server="www.plataformapse.com//www/openc3/" local="128741748940000000" remote="130849131000000000" Dst="0" />
<file name="._license.txt" server="www.plataformapse.com//www/openc3/" local="128741748940000000" remote="130849131000000000" Dst="0" />
<file name="._modalbox.css" server="www.plataformapse.com//www/openc3/" local="128741748940000000" remote="130849131000000000" Dst="0" />
<file name="._.DS_Store" server="192.168.0.147//var/www/html/openc3/" local="128741748940000000" remote="131238825750000000" Dst="0" />
<file name="._changelog.txt" server="192.168.0.147//var/www/html/openc3/" local="128741748940000000" remote="131238825750000000" Dst="0" />
<file name="._license.txt" server="192.168.0.147//var/www/html/openc3/" local="128741748940000000" remote="131238825750000000" Dst="0" />
<file name="._modalbox.css" server="192.168.0.147//var/www/html/openc3/" local="128741748940000000" remote="131238825750000000" Dst="0" />
<file name="._.DS_Store" server="192.168.2.143//var/www/html/openc3/" local="128741748940000000" remote="131250111890000000" Dst="0" />
<file name="._changelog.txt" server="192.168.2.143//var/www/html/openc3/" local="128741748940000000" remote="131250111890000000" Dst="0" />
<file name="._license.txt" server="192.168.2.143//var/www/html/openc3/" local="128741748940000000" remote="131250111890000000" Dst="0" />
<file name="._modalbox.css" server="192.168.2.143//var/www/html/openc3/" local="128741748940000000" remote="131250111890000000" Dst="0" />
<file name="._.DS_Store" server="10.100.110.150//var/www/html/openc3/" local="128741748940000000" remote="131254554980000000" Dst="0" />
<file name="._changelog.txt" server="10.100.110.150//var/www/html/openc3/" local="128741748940000000" remote="131254554980000000" Dst="0" />
<file name="._license.txt" server="10.100.110.150//var/www/html/openc3/" local="128741748940000000" remote="131254554980000000" Dst="0" />
<file name="._modalbox.css" server="10.100.110.150//var/www/html/openc3/" local="128741748940000000" remote="131254554980000000" Dst="0" />
</dwsync>