<?xml version="1.0" encoding="utf-8" ?>
<dwsync>
<file name="block_address.png" server="www.plataformapse.com//www/openc3/" local="129604406040000000" remote="130849132800000000" Dst="0" />
<file name="block_blockquote.png" server="www.plataformapse.com//www/openc3/" local="129604406040000000" remote="130849132800000000" Dst="0" />
<file name="block_div.png" server="www.plataformapse.com//www/openc3/" local="129604406040000000" remote="130849132800000000" Dst="0" />
<file name="block_h1.png" server="www.plataformapse.com//www/openc3/" local="129604406040000000" remote="130849132800000000" Dst="0" />
<file name="block_h2.png" server="www.plataformapse.com//www/openc3/" local="129604406040000000" remote="130849132800000000" Dst="0" />
<file name="block_h3.png" server="www.plataformapse.com//www/openc3/" local="129604406040000000" remote="130849132800000000" Dst="0" />
<file name="block_h4.png" server="www.plataformapse.com//www/openc3/" local="129604406040000000" remote="130849132800000000" Dst="0" />
<file name="block_h5.png" server="www.plataformapse.com//www/openc3/" local="129604406040000000" remote="130849132800000000" Dst="0" />
<file name="block_h6.png" server="www.plataformapse.com//www/openc3/" local="129604406040000000" remote="130849132800000000" Dst="0" />
<file name="block_p.png" server="www.plataformapse.com//www/openc3/" local="129604406040000000" remote="130849132800000000" Dst="0" />
<file name="block_pre.png" server="www.plataformapse.com//www/openc3/" local="129604406040000000" remote="130849132800000000" Dst="0" />
<file name="block_address.png" server="192.168.0.147//var/www/html/openc3/" local="129604406040000000" remote="131238827040000000" Dst="0" />
<file name="block_blockquote.png" server="192.168.0.147//var/www/html/openc3/" local="129604406040000000" remote="131238827040000000" Dst="0" />
<file name="block_div.png" server="192.168.0.147//var/www/html/openc3/" local="129604406040000000" remote="131238827040000000" Dst="0" />
<file name="block_h1.png" server="192.168.0.147//var/www/html/openc3/" local="129604406040000000" remote="131238827040000000" Dst="0" />
<file name="block_h2.png" server="192.168.0.147//var/www/html/openc3/" local="129604406040000000" remote="131238827040000000" Dst="0" />
<file name="block_h3.png" server="192.168.0.147//var/www/html/openc3/" local="129604406040000000" remote="131238827040000000" Dst="0" />
<file name="block_h4.png" server="192.168.0.147//var/www/html/openc3/" local="129604406040000000" remote="131238827040000000" Dst="0" />
<file name="block_h5.png" server="192.168.0.147//var/www/html/openc3/" local="129604406040000000" remote="131238827050000000" Dst="0" />
<file name="block_h6.png" server="192.168.0.147//var/www/html/openc3/" local="129604406040000000" remote="131238827050000000" Dst="0" />
<file name="block_p.png" server="192.168.0.147//var/www/html/openc3/" local="129604406040000000" remote="131238827050000000" Dst="0" />
<file name="block_pre.png" server="192.168.0.147//var/www/html/openc3/" local="129604406040000000" remote="131238827050000000" Dst="0" />
<file name="block_address.png" server="192.168.2.143//var/www/html/openc3/" local="129604406040000000" remote="131250113250000000" Dst="0" />
<file name="block_blockquote.png" server="192.168.2.143//var/www/html/openc3/" local="129604406040000000" remote="131250113260000000" Dst="0" />
<file name="block_div.png" server="192.168.2.143//var/www/html/openc3/" local="129604406040000000" remote="131250113260000000" Dst="0" />
<file name="block_h1.png" server="192.168.2.143//var/www/html/openc3/" local="129604406040000000" remote="131250113260000000" Dst="0" />
<file name="block_h2.png" server="192.168.2.143//var/www/html/openc3/" local="129604406040000000" remote="131250113260000000" Dst="0" />
<file name="block_h3.png" server="192.168.2.143//var/www/html/openc3/" local="129604406040000000" remote="131250113260000000" Dst="0" />
<file name="block_h4.png" server="192.168.2.143//var/www/html/openc3/" local="129604406040000000" remote="131250113260000000" Dst="0" />
<file name="block_h5.png" server="192.168.2.143//var/www/html/openc3/" local="129604406040000000" remote="131250113260000000" Dst="0" />
<file name="block_h6.png" server="192.168.2.143//var/www/html/openc3/" local="129604406040000000" remote="131250113260000000" Dst="0" />
<file name="block_p.png" server="192.168.2.143//var/www/html/openc3/" local="129604406040000000" remote="131250113260000000" Dst="0" />
<file name="block_pre.png" server="192.168.2.143//var/www/html/openc3/" local="129604406040000000" remote="131250113260000000" Dst="0" />
<file name="block_address.png" server="10.100.110.150//var/www/html/openc3/" local="129604406040000000" remote="131254555220000000" Dst="0" />
<file name="block_blockquote.png" server="10.100.110.150//var/www/html/openc3/" local="129604406040000000" remote="131254555220000000" Dst="0" />
<file name="block_div.png" server="10.100.110.150//var/www/html/openc3/" local="129604406040000000" remote="131254555220000000" Dst="0" />
<file name="block_h1.png" server="10.100.110.150//var/www/html/openc3/" local="129604406040000000" remote="131254555220000000" Dst="0" />
<file name="block_h2.png" server="10.100.110.150//var/www/html/openc3/" local="129604406040000000" remote="131254555220000000" Dst="0" />
<file name="block_h3.png" server="10.100.110.150//var/www/html/openc3/" local="129604406040000000" remote="131254555220000000" Dst="0" />
<file name="block_h4.png" server="10.100.110.150//var/www/html/openc3/" local="129604406040000000" remote="131254555220000000" Dst="0" />
<file name="block_h5.png" server="10.100.110.150//var/www/html/openc3/" local="129604406040000000" remote="131254555220000000" Dst="0" />
<file name="block_h6.png" server="10.100.110.150//var/www/html/openc3/" local="129604406040000000" remote="131254555220000000" Dst="0" />
<file name="block_p.png" server="10.100.110.150//var/www/html/openc3/" local="129604406040000000" remote="131254555220000000" Dst="0" />
<file name="block_pre.png" server="10.100.110.150//var/www/html/openc3/" local="129604406040000000" remote="131254555220000000" Dst="0" />
</dwsync>