<?xml version="1.0" encoding="utf-8" ?><dwsync><file name="dist_emi_csv_cron_4.php" server="192.168.0.16//var/www/html/openc3/" local="3558715713" remote="3558715713" Dst="-1" /><file name="dist_emi_csv_cron_2.php" server="192.168.0.16//var/www/html/openc3/" local="3558715725" remote="3558715725" Dst="-1" /><file name="dist_emi_csv_cron_7.php" server="192.168.0.16//var/www/html/openc3/" local="3562447390" remote="3562447390" Dst="-1" /><file name="dist_emi_csv_cron_3.php" server="192.168.0.16//var/www/html/openc3/" local="3558715650" remote="3558715650" Dst="-1" /><file name="dist_emi_csv_cron_5.php" server="192.168.0.16//var/www/html/openc3/" local="3558715726" remote="3558715726" Dst="-1" /><file name="dist_emi_csv_cron.php" server="192.168.0.16//var/www/html/openc3/" local="3558715722" remote="3558715722" Dst="-1" /><file name="dist_emi_csv_cron_6.php" server="192.168.0.16//var/www/html/openc3/" local="3562451536" remote="3562451536" Dst="-1" /><file name="dist_emi_csv_cron_8.php" server="192.168.0.16//var/www/html/openc3/" local="3558715726" remote="3558715726" Dst="-1" /></dwsync>